luhncheck/__init__.py
luhncheck/py.typed
luhncheck-2.3.0.dist-info/METADATA
luhncheck-2.3.0.dist-info/WHEEL
luhncheck-2.3.0.dist-info/licenses/LICENSE
luhncheck-2.3.0.dist-info/RECORD
