Metadata-Version: 2.4
Name: luhncheck
Version: 2.3.0
Summary: Simple validator for identification numbers based on the Luhn algorithm
Project-URL: Repository, https://github.com/dralshehri/luhncheck
Project-URL: Issues, https://github.com/dralshehri/luhncheck/issues
Project-URL: Changelog, https://github.com/dralshehri/luhncheck/blob/main/CHANGELOG.md
Author: Mohammed Alshehri
License-Expression: MIT
License-File: LICENSE
Keywords: credit-card,identification,imei,luhn,validator
Classifier: Development Status :: 5 - Production/Stable
Classifier: Intended Audience :: Developers
Classifier: Operating System :: OS Independent
Classifier: Programming Language :: Python
Classifier: Programming Language :: Python :: 3
Classifier: Programming Language :: Python :: 3.10
Classifier: Programming Language :: Python :: 3.11
Classifier: Programming Language :: Python :: 3.12
Classifier: Programming Language :: Python :: 3.13
Classifier: Programming Language :: Python :: 3.14
Classifier: Topic :: Utilities
Classifier: Typing :: Typed
Requires-Python: >=3.10
